focustuner/Tuner.py
focustuner/__init__.py
focustuner-0.2.10.dist-info/licenses/LICENSE
focustuner-0.2.10.dist-info/METADATA
focustuner-0.2.10.dist-info/WHEEL
focustuner-0.2.10.dist-info/top_level.txt
focustuner-0.2.10.dist-info/RECORD
