Metadata-Version: 2.4
Name: focustuner
Version: 0.2.10
Summary: Python Instrument Control for Focus Mechanical Load tuner CCMT 1808
Author-email: Grace Gomez <grace.gomez@colorado.edu>
Project-URL: Homepage, https://github.com/RFPAL-Github-Organization/LoadTuner-repo
Classifier: Programming Language :: Python :: 3
Classifier: Operating System :: OS Independent
Requires-Python: >=3.8
License-File: LICENSE
Dynamic: license-file
